{
  "collectionName": "components_shared_product_slides",
  "info": {
    "displayName": "Product Slide",
    "description": ""
  },
  "options": {},
  "attributes": {
    "name": {
      "type": "string",
      "pluginOptions": {
        "i18n": {
          "localized": true
        }
      }
    },
    "description": {
      "type": "text",
      "pluginOptions": {
        "i18n": {
          "localized": true
        }
      }
    },
    "image": {
      "type": "media",
      "allowedTypes": [
        "images"
      ],
      "multiple": false,
      "required": false,
      "pluginOptions": {
        "i18n": {
          "localized": false
        }
      }
    },
    "link": {
      "type": "string",
      "pluginOptions": {
        "i18n": {
          "localized": true
        }
      }
    }
  }
}
